yowlayer_store/layer_interface.py
yowlayer_store/layer.py
yowlayer_store/admin.py
yowlayer_store/__init__.py
yowlayer_store/templates/yowlayer_store/base.html
yowlayer_store/models/messages.py
yowlayer_store/models/contacts.py
yowlayer_store/models/conversations.py
yowlayer_store/models/__init__.py
yowlayer_store/migrations/0002_auto_20160104_1602.py
yowlayer_store/migrations/0001_initial.py
yowlayer_store/migrations/__init__.py
yowlayer_store/static/css/yowlayer_store.css
yowlayer_store/static/js/yowlayer_store.js
yowlayer_django_store-0.1.5.dist-info/METADATA
yowlayer_django_store-0.1.5.dist-info/RECORD
yowlayer_django_store-0.1.5.dist-info/top_level.txt
yowlayer_django_store-0.1.5.dist-info/metadata.json
yowlayer_django_store-0.1.5.dist-info/WHEEL
yowlayer_django_store-0.1.5.dist-info/DESCRIPTION.rst
