Metadata-Version: 2.0
Name: yowlayer-django-store
Version: 0.1.5
Summary: Storage layer for yowsup in django
Home-page: https://github.com/jlmadurga/yowlayer-django-store
Author: Juan Madurga
Author-email: jlmadurga@gmail.com
License: GPL-3+
Keywords: yowlayer-django-store
Platform: UNKNOWN
Classifier: Development Status :: 3 - Alpha
Classifier: Framework :: Django
Classifier: Framework :: Django :: 1.8
Classifier: Intended Audience :: Developers
Classifier: License :: OSI Approved :: GNU General Public License v3 or later (GPLv3+)
Classifier: Natural Language :: English
Classifier: Programming Language :: Python :: 2
Classifier: Programming Language :: Python :: 2.7
Classifier: Programming Language :: Python :: 3
Classifier: Programming Language :: Python :: 3.4
Classifier: Programming Language :: Python :: 3.5
